{"stats":{"minecraft:picked_up":{"minecraft:flower_pot":1,"gnumus:gnumus_claw":1,"biomesoplenty:red_maple_sapling":431,"soulsweapons:moonstone":11,"minecraft:enchanted_book":1,"minecraft:stone_brick_stairs":7,"born_in_chaos_v1:black_argillite":5,"minecraft:string":7,"minecraft:soul_soil":3,"minecraft:raw_copper":460,"create:andesite_funnel":1,"create:water_wheel":1,"minecraft:smooth_stone":2,"create:mechanical_press":2,"minecraft:cobbled_deepslate":1393,"biomesoplenty:fir_planks":1,"minecraft:bucket":1,"minecraft:spruce_planks":24,"minecraft:redstone_torch":1,"minecraft:cobblestone_slab":85,"minecraft:azalea":2,"just_in_cave:chromium":2,"minecraft:furnace":56,"minecraft:stick":323,"create:mechanical_mixer":1,"born_in_chaos_v1:shattered_skull":2,"minecraft:oak_fence":1,"minecraft:torch":79,"ecologics:coconut_seedling":4,"create:andesite_casing":41,"epicfight:skillbook":3,"mcwstairs:spruce_compact_stairs":3,"born_in_chaos_v1:pileof_dark_metal":1,"psg:sulphur":31,"tombstone:grave_dust":10,"minecraft:diorite":10,"stalwart_dungeons:soul_magma_bricks":2,"create:large_cogwheel":5,"minecraft:rotten_flesh":51,"create:scoria":4,"farmersdelight:onion":6,"minecraft:blackstone_wall":1,"ecologics:coconut_log":13,"minecraft:iron_block":4,"minecraft:cyan_terracotta":24,"create:veridium":34,"minecraft:obsidian":16,"alexsmobs:flying_fish":1,"minecraft:cobblestone":5363,"create:fluid_tank":3,"minecraft:iron_door":1,"born_in_chaos_v1:spiritual_dust":5,"minecraft:andesite":18,"biomesoplenty:maple_fence":1,"minecraft:chiseled_quartz_block":2,"minecraft:potato":1,"biomesoplenty:fir_sapling":21,"biomesoplenty:fir_log":95,"minecraft:flint":2,"minecraft:tuff":69,"create:raw_zinc":19,"minecraft:dirt":1082,"biomesoplenty:maple_boat":1,"minecraft:lapis_lazuli":125,"minecraft:lantern":2,"power:music_guitar":3,"gnumus:gnumus_pouch_2":1,"born_in_chaos_v1:monster_skin":5,"minecraft:bone":21,"minecraft:stonecutter":1,"minecraft:wheat_seeds":32,"create:shaft":10,"tacz:gun_smith_table":1,"minecraft:oak_planks":7,"psg:raw_potassium":9,"create:cogwheel":13,"create:empty_blaze_burner":1,"minecraft:sand":30,"minecraft:jungle_planks":3,"minecraft:stripped_spruce_log":62,"biomesoplenty:maple_stairs":7,"minecraft:barrel":7,"power:music_stone":4,"minecraft:light_gray_concrete":11,"minecraft:diamond":18,"biomesoplenty:maple_trapdoor":3,"minecraft:bone_meal":2,"soulsweapons:verglas":16,"minecraft:emerald":1,"minecraft:bread":7,"born_in_chaos_v1:rotten_fish":2,"minecraft:oak_sapling":27,"minecraft:netherrack":48,"create:precision_mechanism":1,"minecraft:charcoal":39,"minecraft:mud":1,"minecraft:crafting_table":5,"born_in_chaos_v1:diamond_termite_shard":2,"minecraft:allium":24,"minecraft:clay_ball":12,"born_in_chaos_v1:seedof_chaos":4,"stalwart_dungeons:soul_bricks":32,"create:fluid_pipe":1,"biomesoplenty:maple_planks":87,"tacz:ammo":720,"create:chute":1,"quark:spruce_chest":5,"create:brass_funnel":1,"minecraft:beef":8,"minecraft:iron_nugget":48,"minecraft:spruce_slab":2,"minecraft:sugar_cane":66,"minecraft:raw_iron":204,"ecologics:coconut_slice":2,"minecraft:copper_ingot":5,"minecraft:polished_blackstone_bricks":7,"born_in_chaos_v1:pieceofdarkmetal":8,"minecraft:redstone":10,"create:steam_engine":3,"create:vertical_gearbox":15,"minecraft:arrow":3,"minecraft:stone_shovel":4,"stalwart_dungeons:raw_tungsten":22,"minecraft:jungle_stairs":1,"tombstone:gemstone_of_guardian":1,"minecraft:hay_block":5,"create:depot":2,"minecraft:totem_of_undying":1,"gnumus:mouse_skin":2,"minecraft:glow_berries":1,"minecraft:bone_block":3,"born_in_chaos_v1:fused_bone":2,"minecraft:stripped_oak_log":2,"born_in_chaos_v1:corpse_maggot":18,"minecraft:clock":1,"minecraft:basalt":14,"born_in_chaos_v1:monster_flesh":8,"minecraft:golden_carrot":1,"minecraft:leather":11,"gnumus:gnumus_pouch":2,"royalvariations:spiritual_crown_shard":2,"minecraft:oak_log":30,"create:andesite_alloy":64,"minecraft:lily_pad":16,"tombstone:gift":1,"create:item_vault":2,"minecraft:apple":1,"minecraft:stone_bricks":1,"minecraft:kelp":374,"biomesoplenty:maple_log":875,"minecraft:iron_ingot":3,"minecraft:stone_pickaxe":31,"biomesoplenty:stripped_maple_log":33,"tombstone:bag_of_seeds":1,"minecraft:flowering_azalea":1,"minecraft:soul_sand":38,"biomesoplenty:waterlily":5,"create:mechanical_bearing":1,"minecraft:smooth_basalt":3,"minecraft:sweet_berries":11,"minecraft:dandelion":1,"born_in_chaos_v1:ethereal_spirit":8,"minecraft:quartz":8,"minecraft:gravel":46,"born_in_chaos_v1:dark_rod":2,"minecraft:spruce_sapling":88,"born_in_chaos_v1:fangofthe_hound_leader":3,"minecraft:spruce_log":712,"create:millstone":2,"just_in_wizard_hat:air_element":1,"tacz:modern_kinetic_gun":1,"minecraft:warped_roots":1,"biomesoplenty:maple_slab":13,"tombstone:magic_scroll":1,"minecraft:coal":40,"minecraft:hopper":3},"minecraft:mined":{"create:deepslate_zinc_ore":2,"minecraft:spruce_planks":28,"create:andesite_casing":41,"minecraft:red_nether_bricks":1,"biomesoplenty:maple_slab":12,"minecraft:obsidian":17,"minecraft:cave_vines_plant":14,"biomesoplenty:red_maple_leaves":5,"minecraft:grass_block":612,"minecraft:cracked_polished_blackstone_bricks":36,"minecraft:soul_soil":5,"create:item_vault":3,"minecraft:hopper":3,"tacz:gun_smith_table":1,"minecraft:spawner":4,"minecraft:smooth_stone":2,"minecraft:polished_blackstone_bricks":70,"minecraft:tall_seagrass":22,"minecraft:iron_ore":128,"minecraft:barrel":7,"minecraft:red_nether_brick_stairs":1,"minecraft:fire":6,"minecraft:cobbled_deepslate":8,"minecraft:deepslate_lapis_ore":18,"minecraft:cave_vines":15,"stalwart_dungeons:soul_magma_bricks":3,"minecraft:light_gray_concrete":15,"minecraft:azalea":3,"minecraft:iron_block":2,"create:veridium":56,"create:mechanical_press":2,"minecraft:deepslate_redstone_ore":2,"biomesoplenty:maple_log":48,"biomesoplenty:maple_stairs":10,"create:cogwheel":3,"minecraft:cyan_terracotta":35,"minecraft:kelp_plant":67,"create:steam_engine":3,"minecraft:blackstone":2,"soulsweapons:verglas_ore_deepslate":7,"minecraft:soul_fire":5,"minecraft:clay":3,"soulsweapons:moonstone_ore":2,"minecraft:torch":34,"minecraft:chiseled_quartz_block":2,"minecraft:jungle_stairs":1,"biomesoplenty:stripped_maple_log":33,"create:scoria":16,"mcwstairs:spruce_compact_stairs":3,"minecraft:nether_quartz_ore":8,"minecraft:cobblestone":288,"biomesoplenty:tall_white_lavender":3,"minecraft:oak_planks":6,"minecraft:sugar_cane":39,"minecraft:iron_door":1,"minecraft:wall_torch":15,"minecraft:deepslate_copper_ore":19,"minecraft:seagrass":13,"create:andesite_belt_funnel":2,"minecraft:repeater":1,"biomesoplenty:huge_lily_pad":22,"minecraft:mud":1,"create:mechanical_mixer":1,"biomesoplenty:maple_planks":89,"minecraft:stone_brick_stairs":7,"biomesoplenty:waterlily":5,"minecraft:grass":95,"minecraft:oak_log":29,"biomesoplenty:maple_fence":1,"minecraft:dirt":567,"minecraft:sand":34,"minecraft:smooth_quartz":2,"minecraft:smooth_basalt":3,"minecraft:dispenser":1,"minecraft:stonecutter":1,"minecraft:netherrack":48,"biomesoplenty:white_lavender":2,"minecraft:oak_leaves":46,"minecraft:deepslate":2284,"soulsweapons:verglas_ore":8,"create:zinc_ore":19,"create:brass_funnel":1,"minecraft:tuff":445,"create:millstone":2,"biomesoplenty:maple_trapdoor":3,"stalwart_dungeons:soul_bricks":35,"minecraft:deepslate_diamond_ore":18,"minecraft:blackstone_wall":1,"create:fluid_tank":3,"born_in_chaos_v1:infected_diamond_ore":1,"psg:sulphur_ore":11,"biomesoplenty:bush":39,"minecraft:allium":9,"create:large_cogwheel":4,"minecraft:jungle_planks":3,"born_in_chaos_v1:black_argillite":5,"create:depot":2,"minecraft:redstone_wire":1,"minecraft:spruce_leaves":6,"minecraft:moss_block":1,"minecraft:kelp":8,"minecraft:hay_block":5,"farmersdelight:wild_onions":4,"minecraft:black_stained_glass_pane":2,"create:shaft":12,"gnumus:scion_weed":1,"minecraft:spruce_sapling":2,"minecraft:furnace":75,"minecraft:andesite":25,"minecraft:stripped_spruce_log":62,"treechop:chopped_log":113,"soulsweapons:moonstone_ore_deepslate":9,"minecraft:cobblestone_slab":5,"minecraft:deepslate_iron_ore":77,"create:chute":1,"minecraft:lantern":1,"minecraft:stripped_oak_log":2,"minecraft:packed_ice":9,"minecraft:stone":5087,"minecraft:bone_block":3,"minecraft:podzol":8,"minecraft:flowering_azalea":1,"minecraft:glass_pane":1,"minecraft:soul_sand":38,"psg:potassium_ore":6,"minecraft:basalt":21,"minecraft:dandelion":1,"psg:deepslate_sulphur_ore":11,"minecraft:crafting_table":4,"create:fluid_pipe":1,"minecraft:warped_roots":2,"create:water_wheel":1,"minecraft:copper_ore":118,"minecraft:stone_slab":1,"minecraft:tall_grass":9,"minecraft:lapis_ore":3,"minecraft:lily_pad":22,"minecraft:diorite":12,"stalwart_dungeons:tungsten_ore":28,"create:blaze_burner":1,"create:gearbox":6,"biomesoplenty:red_maple_leaf_pile":21,"minecraft:sweet_berry_bush":8,"minecraft:spruce_log":10,"create:mechanical_bearing":1,"minecraft:coal_ore":43,"minecraft:flower_pot":1,"quark:spruce_chest":5,"minecraft:gravel":15,"minecraft:stone_bricks":1,"minecraft:fern":44},"minecraft:crafted":{"minecraft:brick":3,"biomesoplenty:maple_slab":342,"minecraft:smooth_stone":1,"minecraft:oak_planks":256,"minecraft:cobblestone_slab":72,"minecraft:barrel":91,"minecraft:lightning_rod":3,"minecraft:stone":69,"biomesoplenty:maple_boat":1,"create:item_vault":3,"create:mechanical_bearing":1,"create:deployer":3,"create:vertical_gearbox":12,"minecraft:glass":23,"minecraft:hopper":4,"create:andesite_funnel":2,"minecraft:iron_boots":1,"soulsweapons:moonstone_axe":1,"create:mechanical_press":1,"biomesoplenty:fir_slab":6,"psg:potassium":9,"minecraft:oak_button":2,"minecraft:copper_block":3,"vanillaplustools:stone_shovel":1,"create:brass_funnel":2,"minecraft:stone_bricks":64,"create:cogwheel":118,"create_dd:coal_piece":432,"create:brass_hand":3,"minecraft:flower_pot":1,"stalwart_dungeons:tungsten_hammer":1,"create:depot":3,"create:rose_quartz":8,"minecraft:cooked_porkchop":5,"minecraft:crafting_table":23,"minecraft:spruce_planks":1764,"create:fluid_pipe":8,"tacz:ammo_box":1,"psg:saltpetre":18,"minecraft:wooden_pickaxe":9,"minecraft:baked_potato":9,"minecraft:iron_helmet":1,"minecraft:copper_ingot":377,"create:sand_paper":6,"minecraft:campfire":4,"create:encased_chain_drive":2,"create:mechanical_mixer":1,"biomesoplenty:maple_fence":30,"biomesoplenty:fir_planks":88,"minecraft:stone_brick_stairs":12,"minecraft:iron_chestplate":1,"minecraft:paper":6,"create:water_wheel":15,"minecraft:charcoal":54,"soulsweapons:moonstone_shovel":1,"minecraft:stick":100,"quark:oak_chest":1,"create:mechanical_pump":1,"minecraft:iron_ingot":249,"minecraft:iron_pickaxe":3,"minecraft:iron_block":2,"minecraft:stone_sword":1,"minecraft:gold_ingot":52,"create:large_cogwheel":53,"create:empty_blaze_burner":10,"biomesoplenty:maple_trapdoor":18,"create:chute":4,"vanillaplustools:wooden_hammer":1,"minecraft:stone_shovel":10,"minecraft:coal":54,"create:wrench":1,"vanillaplustools:stone_hammer":9,"create:steam_engine":3,"minecraft:iron_nugget":549,"ecologics:coconut_planks":52,"biomesoplenty:maple_planks":1428,"minecraft:furnace":42,"minecraft:bone_meal":48,"minecraft:flint_and_steel":1,"minecraft:iron_axe":5,"minecraft:spruce_slab":12,"create:millstone":1,"ecologics:coconut_slab":30,"minecraft:stone_pickaxe":81,"create:fluid_tank":56,"soulsweapons:moonstone_pickaxe":1,"create:basin":1,"create:electron_tube":4,"quark:spruce_chest":33,"create:belt_connector":2,"minecraft:wheat":45,"stalwart_dungeons:tungsten_ingot":22,"minecraft:cooked_beef":13,"minecraft:sugar":22,"create:andesite_alloy":244,"mcwstairs:spruce_compact_stairs":60,"minecraft:dried_kelp":16,"create:large_water_wheel":14,"biomesoplenty:maple_stairs":56,"tacz:gun_smith_table":1,"minecraft:bucket":1,"minecraft:stone_axe":1,"minecraft:air":0,"minecraft:bread":15,"create:whisk":1,"minecraft:white_wool":3,"minecraft:raw_gold":45,"minecraft:gunpowder":90,"minecraft:iron_shovel":1,"minecraft:iron_leggings":1,"minecraft:white_bed":1,"create:shaft":256,"minecraft:torch":384,"create:zinc_ingot":19,"biomesoplenty:maple_door":3},"minecraft:killed_by":{"born_in_chaos_v1:nightmare_stalker":1,"minecraft:pillager":1,"enemyexpansion:slugger":1,"born_in_chaos_v1:baby_skeleton":1,"born_in_chaos_v1:corpse_fly":2,"minecraft:blaze":1,"born_in_chaos_v1:bone_imp":1,"creeperoverhaul:dripstone_creeper":1,"born_in_chaos_v1:bonescaller":1,"mutantmonsters:mutant_skeleton":1},"minecraft:broken":{"minecraft:stone_sword":1,"vanillaplustools:stone_hammer":8,"minecraft:iron_axe":4,"minecraft:iron_pickaxe":1,"create:sand_paper":1},"minecraft:killed":{"born_in_chaos_v1:zombie_lumberjack":1,"born_in_chaos_v1:restless_spirit":5,"minecraft:spider":2,"born_in_chaos_v1:siamese_skeletonsright":2,"born_in_chaos_v1:baby_skeleton_minion":6,"born_in_chaos_v1:scarlet_persecutor":4,"minecraft:skeleton":22,"gnumus:pitcher_mousse":3,"born_in_chaos_v1:skeleton_thrasher":1,"soulsweapons:evil_forlorn":2,"alexsmobs:straddler":3,"minecraft:piglin_brute":2,"minecraft:magma_cube":15,"minecraft:piglin":2,"born_in_chaos_v1:bonescaller":3,"born_in_chaos_v1:diamond_termite":3,"minecraft:zombie_villager":1,"born_in_chaos_v1:bone_imp":1,"minecraft:creeper":1,"gnumus:marsupial_mousse":1,"minecraft:pillager":1,"enemyexpansion:meature":1,"minecraft:zombie":11,"born_in_chaos_v1:dread_hound":4,"born_in_chaos_v1:corpse_fly":14,"born_in_chaos_v1:door_knight":1,"minecraft:cow":4,"minecraft:evoker":1,"benssharks:bull_shark":1,"enemyexpansion:direwolf":4,"born_in_chaos_v1:zombie_bruiser":2,"born_in_chaos_v1:maggot":5,"born_in_chaos_v1:baby_spider":5,"born_in_chaos_v1:dire_hound_leader":1,"gnumus:gnumus_hunter":3,"born_in_chaos_v1:corpse_fish":6,"minecraft:drowned":1,"born_in_chaos_v1:spiritof_chaos":1,"born_in_chaos_v1:fallen_chaos_knight":1,"born_in_chaos_v1:baby_skeleton":2,"born_in_chaos_v1:swarmer":1,"quark:foxhound":2,"takesapillage:skirmisher":1,"enemyexpansion:sprinter":1,"born_in_chaos_v1:decrepit_skeleton":9,"royalvariations:royal_zombie":2,"born_in_chaos_v1:decaying_zombie":3,"enemyexpansion:huntsman":1,"born_in_chaos_v1:dark_vortex":1},"minecraft:used":{"minecraft:beetroot":2,"create:deployer":3,"minecraft:iron_shovel":199,"minecraft:bone_block":9,"create:mechanical_bearing":2,"minecraft:iron_chestplate":1,"create:fluid_tank":28,"minecraft:soul_sand":45,"soulsweapons:moonstone_axe":660,"create:cogwheel":20,"create:depot":3,"minecraft:allium":1,"minecraft:axolotl_bucket":1,"minecraft:obsidian":21,"stalwart_dungeons:tungsten_hammer":46,"minecraft:glass":23,"minecraft:cyan_terracotta":20,"minecraft:lantern":2,"minecraft:iron_helmet":1,"create:millstone":3,"create:andesite_funnel":3,"minecraft:stone_brick_stairs":15,"minecraft:stone_bricks":46,"tombstone:gemstone_of_guardian":3,"create:shaft":53,"minecraft:sweet_berries":9,"create:steam_engine":6,"minecraft:furnace":98,"minecraft:potato":3,"biomesoplenty:maple_planks":431,"minecraft:oak_planks":22,"minecraft:sugar_cane":15,"epicfight:skillbook":7,"biomesoplenty:maple_log":563,"power:music_guitar":210,"minecraft:golden_apple":1,"minecraft:glow_berries":1,"minecraft:sand":1,"stalwart_dungeons:soul_bricks":32,"tombstone:villager_gift":1,"minecraft:lightning_rod":3,"born_in_chaos_v1:monster_flesh":4,"minecraft:bread":29,"tombstone:grave_key":13,"minecraft:gravel":5,"biomesoplenty:red_maple_sapling":35,"ecologics:coconut_slice":2,"create:basin":1,"biomesoplenty:maple_stairs":58,"create:vertical_gearbox":17,"biomesoplenty:maple_trapdoor":21,"create:large_cogwheel":10,"minecraft:stone_sword":135,"biomesoplenty:maple_boat":2,"minecraft:flint_and_steel":18,"create:item_vault":6,"minecraft:stone_shovel":94,"tacz:gun_smith_table":2,"minecraft:spruce_planks":1321,"vanillaplustools:stone_hammer":1069,"minecraft:torch":446,"minecraft:dirt":936,"create:mechanical_pump":1,"create:mechanical_mixer":2,"minecraft:hopper":7,"create:chute":2,"quark:spruce_chest":35,"create:wrench":27,"minecraft:iron_axe":1146,"minecraft:iron_boots":1,"stalwart_dungeons:soul_magma_bricks":2,"minecraft:barrel":39,"create:encased_chain_drive":2,"minecraft:basalt":14,"minecraft:golden_carrot":17,"tombstone:gift":5,"biomesoplenty:stripped_maple_log":22,"create:fluid_pipe":4,"ecologics:coconut_seedling":1,"minecraft:cooked_beef":13,"minecraft:cobbled_deepslate":218,"create:belt_connector":2,"mcwstairs:spruce_compact_stairs":51,"minecraft:iron_leggings":1,"minecraft:water_bucket":3,"create:empty_blaze_burner":1,"soulsweapons:moonstone_pickaxe":731,"minecraft:cobblestone_slab":7,"minecraft:stonecutter":1,"create:blaze_burner":10,"minecraft:polished_blackstone_bricks":7,"biomesoplenty:maple_fence":28,"minecraft:crafting_table":27,"create:brass_funnel":2,"vanillaplustools:stone_shovel":22,"minecraft:white_bed":1,"minecraft:campfire":4,"biomesoplenty:maple_door":3,"minecraft:spruce_log":135,"minecraft:flower_pot":2,"minecraft:oak_log":2,"minecraft:apple":1,"vanillaplustools:wooden_hammer":13,"create:mechanical_press":3,"minecraft:oak_button":2,"minecraft:iron_pickaxe":383,"create:water_wheel":1,"minecraft:spruce_sapling":81,"create:large_water_wheel":14,"soulsweapons:moonstone_shovel":843,"minecraft:stone_axe":94,"minecraft:cobblestone":991,"biomesoplenty:maple_slab":149,"minecraft:cooked_porkchop":6,"minecraft:bucket":4,"alexsmobs:animal_dictionary":1,"minecraft:stripped_oak_log":43,"minecraft:kelp":104,"minecraft:splash_potion":1,"minecraft:smooth_stone":2},"minecraft:custom":{"minecraft:interact_with_crafting_table":148,"minecraft:open_barrel":282,"minecraft:leave_game":8,"minecraft:time_since_death":36289,"minecraft:damage_resisted":946,"minecraft:sprint_one_cm":881998,"minecraft:drop":573,"minecraft:talked_to_villager":1,"minecraft:play_time":809906,"minecraft:deaths":18,"minecraft:jump":9433,"minecraft:walk_on_water_one_cm":91958,"minecraft:interact_with_furnace":156,"minecraft:sleep_in_bed":7,"minecraft:waystone_activated":2,"minecraft:damage_dealt":18701,"minecraft:player_kills":3,"minecraft:crouch_one_cm":125403,"tombstone:undead_killed":73,"minecraft:interact_with_anvil":1,"minecraft:mob_kills":176,"minecraft:inspect_hopper":11,"minecraft:damage_dealt_resisted":4391,"minecraft:climb_one_cm":17990,"minecraft:walk_one_cm":3030718,"minecraft:damage_dealt_absorbed":65,"minecraft:sneak_time":25372,"minecraft:walk_under_water_one_cm":82626,"minecraft:boat_one_cm":253980,"minecraft:interact_with_blast_furnace":2,"minecraft:total_world_time":809906,"tombstone:raider_killed":3,"minecraft:tune_noteblock":3,"minecraft:time_since_rest":26785,"minecraft:damage_absorbed":40,"minecraft:damage_taken":9800,"minecraft:swim_one_cm":208706,"minecraft:fly_one_cm":1642077,"minecraft:open_chest":293,"minecraft:fall_one_cm":323114},"minecraft:dropped":{"biomesoplenty:fir_log":2,"create:vertical_gearbox":10,"biomesoplenty:red_maple_sapling":396,"power:music_stone":2,"minecraft:crafting_table":1,"minecraft:leather":7,"minecraft:jungle_planks":1,"born_in_chaos_v1:pieceofdarkmetal":2,"gnumus:mouse_skin":2,"minecraft:flint":1,"minecraft:cyan_terracotta":4,"minecraft:dirt":77,"gnumus:gnumus_claw":1,"biomesoplenty:maple_planks":9,"minecraft:bone":2,"minecraft:stone_axe":1,"minecraft:sugar_cane":2,"biomesoplenty:maple_slab":26,"minecraft:iron_nugget":1,"minecraft:cobbled_deepslate":345,"alexsmobs:animal_dictionary":1,"born_in_chaos_v1:ethereal_spirit":5,"minecraft:rotten_flesh":44,"minecraft:oak_planks":2,"born_in_chaos_v1:seedof_chaos":1,"create:scoria":4,"born_in_chaos_v1:corpse_maggot":8,"minecraft:azalea":2,"gnumus:gnumus_pouch":1,"minecraft:spruce_slab":2,"minecraft:arrow":3,"minecraft:stone_brick_stairs":1,"born_in_chaos_v1:shattered_skull":2,"minecraft:wheat_seeds":28,"minecraft:clock":1,"ecologics:coconut_seedling":2,"minecraft:cobblestone":885,"royalvariations:spiritual_crown_shard":1,"minecraft:copper_ingot":32,"bossominium:the_bossdexium":1,"minecraft:stick":32,"minecraft:iron_block":2,"born_in_chaos_v1:black_argillite":5,"vanillaplustools:wooden_hammer":1,"minecraft:diorite":10,"minecraft:torch":16,"born_in_chaos_v1:fused_bone":2,"tombstone:grave_dust":4,"minecraft:flowering_azalea":1,"minecraft:mud":1,"minecraft:string":3,"minecraft:lily_pad":8,"minecraft:spruce_sapling":2,"minecraft:dandelion":1,"minecraft:sweet_berries":2,"minecraft:kelp":1,"minecraft:raw_copper":13,"minecraft:tuff":5,"born_in_chaos_v1:rotten_fish":2,"minecraft:stone_shovel":4,"born_in_chaos_v1:spiritual_dust":4,"ecologics:coconut_slab":30,"minecraft:potato":1,"minecraft:cobblestone_slab":81,"minecraft:stone":3,"minecraft:allium":7,"create:veridium":34,"biomesoplenty:maple_log":10,"minecraft:piglin_banner_pattern":1,"minecraft:spruce_planks":5,"create:zinc_ingot":16,"minecraft:spruce_log":9,"minecraft:stone_pickaxe":31,"power:music_guitar":3,"create:golden_sheet":1}},"DataVersion":3465}